CMakeLists.txt
LICENSE
README.md
pyproject.toml
setup.py
clipper/clipper.cpp
clipper/clipper.hpp
clipper_py/__init__.py
clipper_py/clipper-py.cpp
clipper_py/clipper-py.h
clipper_py/clipper.cpp
clipper_py/int-point.cpp
clipper_py/path.cpp
clipper_py/poly-tree.cpp
clipper_py.egg-info/PKG-INFO
clipper_py.egg-info/SOURCES.txt
clipper_py.egg-info/dependency_links.txt
clipper_py.egg-info/not-zip-safe
clipper_py.egg-info/top_level.txt