Metadata-Version: 2.1
Name: clipper-py
Version: 0.1.5
Summary: Python Bindings for Clipper using Boost.Python
Home-page: https://github.com/sdedovic/clipper-py
Author: Stevan Dedovic
Author-email: stevan@dedovic.com
License: UNKNOWN
Project-URL: Bug Tracker, https://github.com/sdedovic/clipper-py/issues
Project-URL: Documentation, https://github.com/sdedovic/clipper-py
Project-URL: Source Code, https://github.com/sdedovic/clipper-py
Keywords: clipper polygon clipping polygon-clipping
Platform: UNKNOWN
Classifier: Development Status :: 3 - Alpha
Classifier: Environment :: Other Environment
Classifier: Intended Audience :: Developers
Classifier: Operating System :: POSIX :: Linux
Classifier: Programming Language :: C++
Classifier: Programming Language :: Python :: 3 :: Only
Classifier: License :: OSI Approved
Classifier: License :: OSI Approved :: MIT License
Classifier: Topic :: Multimedia :: Graphics
Classifier: Topic :: Artistic Software
Classifier: Topic :: Scientific/Engineering :: Mathematics
Classifier: Topic :: Software Development :: Libraries :: Python Modules
